<?xml version="1.0" encoding="UTF-8"?>
<!DOCTYPE locale SYSTEM "../../../../../lib/pkp/dtd/locale.dtd">

<!--
  * plugins/themes/criticalTimes/locale/en_US/locale.xml
  *
  * Copyright (c) 2014-2017 Simon Fraser University Library
  * Copyright (c) 2003-2017 John Willinsky
  * Distributed under the GNU GPL v2. For full terms see the file docs/COPYING.
  *
  * Localization strings
  -->

<locale name="en_US" full_name="U.S. English">
	<message key="plugins.themes.criticalTimes.name">Critical Times</message>
	<message key="plugins.themes.criticalTimes.description">A theme for Critical Times, a journal published by the International Consortium of Critical Theory Programs.</message>

	<message key="plugins.themes.criticalTimes.logoAltText">Critical Times Logo</message>
	<message key="plugins.themes.criticalTimes.nav.menu">Menu</message>
	<message key="plugins.themes.criticalTimes.browseArchives.title">Read the Archives</message>
	<message key="plugins.themes.criticalTimes.browseArchives.description">Browse all of our published material by section.</message>
	<message key="plugins.themes.criticalTimes.footer.address"><![CDATA[Stephens Hall<br>University of California, Berkley<br>Berkley, CA 94720-23340]]></message>
	<message key="plugins.themes.criticalTimes.footer.support">Supported by a grant to the University of California, Berkley from the Andrew W. Mellon Foundation.</message>

	<!-- Issue details -->
	<message key="plugins.themes.criticalTimes.issue.specialSection">Special Section</message>

	<!-- Article details -->
	<message key="plugins.themes.criticalTimes.article.galleys">View</message>
	<message key="plugins.themes.criticalTimes.article.galleys.supplementary">Supplementary Files</message>
	<message key="plugins.themes.criticalTimes.article.specialSection">Published in a Special Section</message>
	<message key="plugins.themes.criticalTimes.article.fullIssue">Read the {$link}full issue{$linkEnd}.</message>

	<!-- TOC Configuration -->
	<message key="plugins.themes.criticalTimes.toc.group">Group {$number}</message>
	<message key="plugins.themes.criticalTimes.toc.group.name">Name</message>
	<message key="plugins.themes.criticalTimes.toc.group.description">Description</message>
	<message key="plugins.themes.criticalTimes.toc.group.special">Should articles in this group be identified as a special section?</message>
	<message key="plugins.themes.criticalTimes.toc.group.items">Article IDs</message>
	<message key="plugins.themes.criticalTimes.toc.group.items.description">Article IDs should be separated by a comma, eg - 12,35,67,43</message>
	<message key="plugins.themes.criticalTimes.toc.group1.note">The first group will be displayed next to the title and description for the entire issue.</message>
</locale>
